screg2/RegNMF.py
screg2/__init__.py
screg2/core.py
screg2-0.1.0.dist-info/METADATA
screg2-0.1.0.dist-info/WHEEL
screg2-0.1.0.dist-info/RECORD
