Metadata-Version: 2.1
Name: scReg2
Version: 0.1.0
Summary: scReg2: integrate RNA and ATAC dimention reduction with batch remove
Author: Cham
Author-email: fchang@clemson.edu
Requires-Python: >=3.10,<4.0
Classifier: Programming Language :: Python :: 3
Classifier: Programming Language :: Python :: 3.10
Classifier: Programming Language :: Python :: 3.11
Classifier: Programming Language :: Python :: 3.12
Provides-Extra: docs
Requires-Dist: anndata (>=0.10.6,<0.11.0)
Requires-Dist: harmony-py (>=0.4.14,<0.5.0)
Requires-Dist: muon (>=0.1.6,<0.2.0)
Requires-Dist: numpy (>=1.26.4,<2.0.0)
Requires-Dist: pandas (>=2.1.4,<3.0.0)
Requires-Dist: psutil (>=5.9.0,<6.0.0)
Requires-Dist: scanpy (>=1.9.8,<2.0.0)
Requires-Dist: scikit-learn (>=1.4.1,<2.0.0)
Requires-Dist: scipy (>=1.12.0,<2.0.0)
Requires-Dist: torch (>=2.2.1,<3.0.0)
